{
  "generated_at": "2026-01-05T15:31:31Z",
  "window_minutes": 30,
  "samples": [
    {
      "timestamp": "2026-01-05T15:21:51Z",
      "latency_ms": 1.590625,
      "http_status": 200,
      "success": true
    },
    {
      "timestamp": "2026-01-05T15:21:55Z",
      "latency_ms": 53.455333,
      "http_status": 200,
      "success": true
    },
    {
      "timestamp": "2026-01-05T15:21:55Z",
      "latency_ms": 2.088291,
      "http_status": 500,
      "success": false
    },
    {
      "timestamp": "2026-01-05T15:21:55Z",
      "latency_ms": 1.031917,
      "http_status": 500,
      "success": false
    },
    {
      "timestamp": "2026-01-05T15:21:56Z",
      "latency_ms": 0.983666,
      "http_status": 500,
      "success": false
    },
    {
      "timestamp": "2026-01-05T15:31:27Z",
      "latency_ms": 1.571833,
      "http_status": 200,
      "success": true
    },
    {
      "timestamp": "2026-01-05T15:31:31Z",
      "latency_ms": 54.704333,
      "http_status": 200,
      "success": true
    },
    {
      "timestamp": "2026-01-05T15:31:31Z",
      "latency_ms": 1.641625,
      "http_status": 500,
      "success": false
    },
    {
      "timestamp": "2026-01-05T15:31:31Z",
      "latency_ms": 1.48975,
      "http_status": 500,
      "success": false
    },
    {
      "timestamp": "2026-01-05T15:31:31Z",
      "latency_ms": 1.518292,
      "http_status": 500,
      "success": false
    }
  ],
  "sample_count": 10,
  "p50_ms": 1.581229,
  "p95_ms": 54.142283,
  "success_rate": 0.4
}
